{
    "photos": [{
            "path": "images/japan/kyoto",
            "fileName": "kyoto_station.jpg",
            "title": "",
            "year": "2013",
            "country": "Japan",
            "city": "Kyoto",
            "location": "Kawaramachi Station",
            "classes": ["portrait"],
            "ratio": "z"
        },
        {
            "path": "images/japan/kyoto",
            "fileName": "tako_street_art_kyoto.jpg",
            "title": "",
            "year": "2013",
            "country": "Japan",
            "city": "Kyoto",
            "location": "",
            "classes": ["portrait"],
            "ratio": "z"
        },
        {
            "path": "images/japan/kobe",
            "fileName": "chinatown_kobe_1_3.jpg",
            "title": "",
            "year": "2014",
            "country": "Japan",
            "city": "Kobe",
            "location": "China Town",
            "classes": ["r43"],
            "ratio": "43"
        },
        {
            "path": "images/japan/kobe",
            "fileName": "chinatown_kobe_2.jpg",
            "title": "",
            "year": "2014",
            "country": "Japan",
            "city": "Kobe",
            "location": "China Town",
            "classes": ["r43"],
            "ratio": "43"
        },
        {
            "path": "images/japan/osaka",
            "fileName": "americamura_osaka_43.jpg",
            "title": "",
            "year": "2016",
            "country": "Japan",
            "city": "Osaka",
            "location": "America mura",
            "classes": ["r43"],
            "ratio": "43"
        },
        {
            "path": "images/japan/tokyo",
            "fileName": "shibuya_1_32.jpg",
            "title": "",
            "year": "2016",
            "country": "Japan",
            "city": "Tokyo",
            "location": "Shibuya",
            "classes": ["r32"],
            "ratio": "32"
        },
        {
            "path": "images/korea/seoul",
            "fileName": "hyehwa.jpg",
            "title": "",
            "year": "2014",
            "country": "South Korea",
            "city": "Seoul",
            "location": "Hyehwa",
            "classes": ["r43"],
            "ratio": "43"
        },
        {
            "path": "images/korea/seoul",
            "fileName": "mister_chat_seoul.jpg",
            "title": "",
            "year": "2014",
            "country": "South Korea",
            "city": "Seoul",
            "location": "Hyehwa",
            "classes": ["r43"],
            "ratio": "43"
        },
        {
            "path": "images/korea/seoul",
            "fileName": "jongno_insadong_1.jpg",
            "title": "",
            "year": "2014",
            "country": "South Korea",
            "city": "Seoul",
            "location": "Insadong",
            "classes": ["r43"],
            "ratio": "43"
        },
        {
            "path": "images/korea/seoul",
            "fileName": "hondae_1.jpg",
            "title": "",
            "year": "2014",
            "country": "South Korea",
            "city": "Seoul",
            "location": "Hondea",
            "classes": ["r43"],
            "ratio": "43"
        },
        {
            "path": "images/korea/seoul",
            "fileName": "hyehwa_2.jpg",
            "title": "",
            "year": "2014",
            "country": "South Korea",
            "city": "Seoul",
            "location": "Hyehwa",
            "classes": ["portrait"],
            "ratio": "y"
        },
        {
            "path": "images/korea/seoul",
            "fileName": "hyehwa_3.jpg",
            "title": "",
            "year": "2014",
            "country": "South Korea",
            "city": "Seoul",
            "location": "Hyehwa",
            "classes": ["r43"],
            "ratio": "43"
        },
        {
            "path": "images/korea/seoul",
            "fileName": "hyehwa_4.jpg",
            "title": "",
            "year": "2014",
            "country": "South Korea",
            "city": "Seoul",
            "location": "Hyehwa",
            "classes": ["portrait"],
            "ratio": "z"
        },
        {
            "path": "images/korea/seoul",
            "fileName": "hyehwa_5.jpg",
            "title": "",
            "year": "2014",
            "country": "South Korea",
            "city": "Seoul",
            "location": "Hyehwa",
            "classes": ["portrait"],
            "ratio": "z"
        },
        {
            "path": "images/korea/seoul",
            "fileName": "hyehwa_6.jpg",
            "title": "",
            "year": "2014",
            "country": "South Korea",
            "city": "Seoul",
            "location": "Hyehwa",
            "classes": ["r43"],
            "ratio": "43"
        },
        {
            "path": "images/korea/seoul",
            "fileName": "hyehwa_7.jpg",
            "title": "",
            "year": "2014",
            "country": "South Korea",
            "city": "Seoul",
            "location": "Hyehwa",
            "classes": ["portrait"],
            "ratio": "z"
        },
        {
            "path": "images/korea/seoul",
            "fileName": "hyehwa_8.jpg",
            "title": "",
            "year": "2014",
            "country": "South Korea",
            "city": "Seoul",
            "location": "Hyehwa",
            "classes": ["portrait"],
            "ratio": "z"
        },
        {
            "path": "images/korea/seoul",
            "fileName": "hyehwa_9.jpg",
            "title": "",
            "year": "2014",
            "country": "South Korea",
            "city": "Seoul",
            "location": "Hyehwa",
            "classes": ["r43"],
            "ratio": "43"
        },
        {
            "path": "images/korea/seoul",
            "fileName": "hyehwa_10.jpg",
            "title": "",
            "year": "2014",
            "country": "South Korea",
            "city": "Seoul",
            "location": "Hyehwa",
            "classes": ["r43"],
            "ratio": "43"
        },
        {
            "path": "images/korea/seoul",
            "fileName": "hyehwa_11.jpg",
            "title": "",
            "year": "2014",
            "country": "South Korea",
            "city": "Seoul",
            "location": "Hyehwa",
            "classes": ["r32"],
            "ratio": "32"
        },
        {
            "path": "images/korea/seoul",
            "fileName": "hyehwa_12.jpg",
            "title": "",
            "year": "2014",
            "country": "South Korea",
            "city": "Seoul",
            "location": "Hyehwa",
            "classes": ["portrait"],
            "ratio": "z"
        },
        {
            "path": "images/korea/seoul",
            "fileName": "jongno_insadong_2.jpg",
            "title": "",
            "year": "2014",
            "country": "South Korea",
            "city": "Seoul",
            "location": "Insadong",
            "classes": ["r43"],
            "ratio": "43"
        },
        {
            "path": "images/korea/seoul",
            "fileName": "hyehwa_13.jpg",
            "title": "",
            "year": "2014",
            "country": "South Korea",
            "city": "Seoul",
            "location": "Hyehwa",
            "classes": ["r43"],
            "ratio": "43"
        },
        {
            "path": "images/korea/seoul",
            "fileName": "itaewon_1.jpg",
            "title": "",
            "year": "2014",
            "country": "South Korea",
            "city": "Seoul",
            "location": "Itaewon",
            "classes": ["r43"],
            "ratio": "43"
        },
        {
            "path": "images/korea/seoul",
            "fileName": "hyehwa_14.jpg",
            "title": "",
            "year": "2016",
            "country": "South Korea",
            "city": "Seoul",
            "location": "Hyehwa",
            "classes": ["r32"],
            "ratio": "32"
        },
        {
            "path": "images/korea/seoul",
            "fileName": "hyehwa_15.jpg",
            "title": "",
            "year": "2016",
            "country": "South Korea",
            "city": "Seoul",
            "location": "Hyehwa",
            "classes": ["r43"],
            "ratio": "43"
        },
        {
            "path": "images/korea/seoul",
            "fileName": "hyehwa_16.jpg",
            "title": "",
            "year": "2016",
            "country": "South Korea",
            "city": "Seoul",
            "location": "Hyehwa",
            "classes": ["r43"],
            "ratio": "43"
        },
        {
            "path": "images/france/marseille",
            "fileName": "marseille_01.jpg",
            "title": "",
            "year": "2017",
            "country": "France",
            "city": "Marseille",
            "location": "",
            "classes": ["portrait"],
            "ratio": "z"
        },
        {
            "path": "images/france/marseille",
            "fileName": "marseille_03.jpg",
            "title": "",
            "year": "2017",
            "country": "France",
            "city": "Marseille",
            "location": "",
            "classes": ["r32"],
            "ratio": "32"
        },
        {
            "path": "images/france/marseille",
            "fileName": "marseille_04.jpg",
            "title": "",
            "year": "2017",
            "country": "France",
            "city": "Marseille",
            "location": "",
            "classes": ["r43"],
            "ratio": "43"
        },
        {
            "path": "images/france/marseille",
            "fileName": "marseille_05.jpg",
            "title": "",
            "year": "2017",
            "country": "France",
            "city": "Marseille",
            "location": "",
            "classes": ["wide"],
            "ratio": "wide"
        },
        {
            "path": "images/france/marseille",
            "fileName": "marseille_06.jpg",
            "title": "",
            "year": "2017",
            "country": "France",
            "city": "Marseille",
            "location": "",
            "classes": ["r32"],
            "ratio": "32"
        },
        {
            "path": "images/france/marseille",
            "fileName": "marseille_07.jpg",
            "title": "",
            "year": "2017",
            "country": "France",
            "city": "Marseille",
            "location": "",
            "classes": ["r32"],
            "ratio": "32"
        },
        {
            "path": "images/belgium/brussels",
            "fileName": "brussels_01.jpg",
            "title": "",
            "year": "2016",
            "country": "Belgium",
            "city": "brussels",
            "location": "",
            "classes": ["portrait"],
            "ratio": "z"
        },
        {
            "path": "images/belgium/brussels",
            "fileName": "brussels_02.jpg",
            "title": "",
            "year": "2016",
            "country": "Belgium",
            "city": "brussels",
            "location": "",
            "classes": ["r32"],
            "ratio": "32"
        },
        {
            "path": "images/belgium/brussels",
            "fileName": "brussels_03.jpg",
            "title": "",
            "year": "2016",
            "country": "Belgium",
            "city": "brussels",
            "location": "",
            "classes": ["portrait"],
            "ratio": "z"
        },
        {
            "path": "images/belgium/brussels",
            "fileName": "brussels_04.jpg",
            "title": "",
            "year": "2016",
            "country": "Belgium",
            "city": "brussels",
            "location": "",
            "classes": ["wide"],
            "ratio": "wide"
        },
        {
            "path": "images/belgium/brussels",
            "fileName": "brussels_05.jpg",
            "title": "",
            "year": "2016",
            "country": "Belgium",
            "city": "brussels",
            "location": "",
            "classes": ["r32"],
            "ratio": "32"
        },
        {
            "path": "images/belgium/brussels",
            "fileName": "brussels_06.jpg",
            "title": "",
            "year": "2016",
            "country": "Belgium",
            "city": "brussels",
            "location": "",
            "classes": ["r32"],
            "ratio": "32"
        },
        {
            "path": "images/belgium/brussels",
            "fileName": "brussels_07.jpg",
            "title": "",
            "year": "2016",
            "country": "Belgium",
            "city": "brussels",
            "location": "",
            "classes": ["r32"],
            "ratio": "32"
        },
        {
            "path": "images/usa/san_francisco",
            "fileName": "san_francisco_01.jpg",
            "title": "",
            "year": "2015",
            "country": "USA",
            "city": "San Francisco",
            "location": "",
            "classes": ["r43"],
            "ratio": "43"
        },
        {
            "path": "images/usa/san_francisco",
            "fileName": "san_francisco_04.jpg",
            "title": "",
            "year": "2015",
            "country": "USA",
            "city": "San Francisco",
            "location": "",
            "classes": ["r43"],
            "ratio": "43"
        },
        {
            "path": "images/usa/san_francisco",
            "fileName": "san_francisco_02.jpg",
            "title": "",
            "year": "2015",
            "country": "USA",
            "city": "San Francisco",
            "location": "Market Street",
            "classes": ["r43"],
            "ratio": "43"
        },
        {
            "path": "images/usa/san_francisco",
            "fileName": "san_francisco_03.jpg",
            "title": "",
            "year": "2015",
            "country": "USA",
            "city": "San Francisco",
            "location": "Market Street",
            "classes": ["r32"],
            "ratio": "32"
        },
        {
            "path": "images/australia/sydney",
            "fileName": "bondy_01.jpg",
            "title": "",
            "year": "2017",
            "country": "Australia",
            "city": "Sydney",
            "location": "Bondy Beach",
            "classes": ["r32"],
            "ratio": "32"
        },
        {
            "path": "images/australia/sydney",
            "fileName": "bondy_02.jpg",
            "title": "",
            "year": "2017",
            "country": "Australia",
            "city": "Sydney",
            "location": "Bondy Beach",
            "classes": ["r43"],
            "ratio": "43"
        },
        {
            "path": "images/australia/sydney",
            "fileName": "bondy_03.jpg",
            "title": "",
            "year": "2017",
            "country": "Australia",
            "city": "Sydney",
            "location": "Bondy Beach",
            "classes": ["r43"],
            "ratio": "43"
        },
        {
            "path": "images/australia/sydney",
            "fileName": "bondy_04.jpg",
            "title": "",
            "year": "2017",
            "country": "Australia",
            "city": "Sydney",
            "location": "Bondy Beach",
            "classes": ["r32"],
            "ratio": "32"
        },
        {
            "path": "images/new_zealand/auckland",
            "fileName": "auckland_01.jpg",
            "title": "",
            "year": "2017",
            "country": "New Zealand",
            "city": "Auckland",
            "location": "",
            "classes": ["r43"],
            "ratio": "43"
        },
        {
            "path": "images/new_zealand/auckland",
            "fileName": "auckland_02.jpg",
            "title": "",
            "year": "2017",
            "country": "New Zealand",
            "city": "Auckland",
            "location": "",
            "classes": ["r43"],
            "ratio": "43"
        },
        {
            "path": "images/new_zealand/auckland",
            "fileName": "auckland_03.jpg",
            "title": "",
            "year": "2017",
            "country": "New Zealand",
            "city": "Auckland",
            "location": "",
            "classes": ["r43"],
            "ratio": "43"
        },
        {
            "path": "images/uae/dubai",
            "fileName": "dubai_01.jpg",
            "title": "",
            "year": "2017",
            "country": "UAE",
            "city": "Dubai",
            "location": "Jumeirah",
            "classes": ["r43"],
            "ratio": "43"
        },
        {
            "path": "images/uae/dubai",
            "fileName": "dubai_02.jpg",
            "title": "",
            "year": "2017",
            "country": "UAE",
            "city": "Dubai",
            "location": "Jumeirah",
            "classes": ["r43"],
            "ratio": "43"
        },
        {
            "path": "images/uae/dubai",
            "fileName": "dubai_03.jpg",
            "title": "",
            "year": "2017",
            "country": "UAE",
            "city": "Dubai",
            "location": "Jumeirah",
            "classes": ["r43"],
            "ratio": "43"
        },
        {
            "path": "images/czech_republic/prague",
            "fileName": "prague_01.jpg",
            "title": "",
            "year": "2018",
            "country": "Czech Republic",
            "city": "Prague",
            "location": "Smíchov",
            "classes": ["portrait"],
            "ratio": "z"
        },
        {
            "path": "images/czech_republic/prague",
            "fileName": "prague_02.jpg",
            "title": "",
            "year": "2018",
            "country": "Czech Republic",
            "city": "Prague",
            "location": "",
            "classes": ["r32"],
            "ratio": "32"
        },
        {
            "path": "images/czech_republic/prague",
            "fileName": "prague_03.jpg",
            "title": "",
            "year": "2018",
            "country": "Czech Republic",
            "city": "Prague",
            "location": "Žižkov",
            "classes": ["r43"],
            "ratio": "43"
        },
        {
            "path": "images/germany/berlin",
            "fileName": "berlin_01.jpg",
            "title": "",
            "year": "2018",
            "country": "Germany",
            "city": "Berlin",
            "location": "East Side Gallery",
            "classes": ["r43"],
            "ratio": "43"
        },
        {
            "path": "images/germany/berlin",
            "fileName": "berlin_02.jpg",
            "title": "",
            "year": "2018",
            "country": "Germany",
            "city": "Berlin",
            "location": "East Side Gallery",
            "classes": ["r32"],
            "ratio": "32"
        },
        {
            "path": "images/germany/berlin",
            "fileName": "berlin_03.jpg",
            "title": "",
            "year": "2018",
            "country": "Germany",
            "city": "Berlin",
            "location": "East Side Gallery",
            "classes": ["r43"],
            "ratio": "43"
        },
        {
            "path": "images/france/orleans",
            "fileName": "orleans_01.jpg",
            "title": "",
            "year": "2017",
            "country": "France",
            "city": "Orléans",
            "location": "",
            "classes": ["r32"],
            "ratio": "32"
        },
        {
            "path": "images/france/orleans",
            "fileName": "orleans_02.jpg",
            "title": "",
            "year": "2017",
            "country": "France",
            "city": "Orléans",
            "location": "",
            "classes": ["r32"],
            "ratio": "32"
        },
        {
            "path": "images/france/orleans",
            "fileName": "orleans_03.jpg",
            "title": "",
            "year": "2014",
            "country": "France",
            "city": "Orléans",
            "location": "",
            "classes": ["r43"],
            "ratio": "43"
        },
        {
            "path": "images/france/strasbourg",
            "fileName": "strasbourg_01.jpg",
            "title": "",
            "year": "2017",
            "country": "France",
            "city": "Strasbourg",
            "location": "",
            "classes": ["r43"],
            "ratio": "43"
        },
        {
            "path": "images/france/strasbourg",
            "fileName": "strasbourg_02.jpg",
            "title": "",
            "year": "2017",
            "country": "France",
            "city": "Strasbourg",
            "location": "",
            "classes": ["r32"],
            "ratio": "32"
        },
        {
            "path": "images/france/strasbourg",
            "fileName": "mister_chat_strasbourg.jpg",
            "title": "",
            "year": "2015",
            "country": "France",
            "city": "Strasbourg",
            "location": "",
            "classes": ["portrait"],
            "ratio": "z"
        },
        {
            "path": "images/france/paris",
            "fileName": "paris_01.jpg",
            "title": "",
            "year": "2014",
            "country": "France",
            "city": "Paris",
            "location": "",
            "classes": ["r43"],
            "ratio": "43"
        },
        {
            "path": "images/france/paris",
            "fileName": "paris_02.jpg",
            "title": "",
            "year": "2014",
            "country": "France",
            "city": "Paris",
            "location": "Montmartre",
            "classes": ["r43"],
            "ratio": "43"
        },
        {
            "path": "images/france/paris",
            "fileName": "paris_03.jpg",
            "title": "",
            "year": "2014",
            "country": "France",
            "city": "Paris",
            "location": "",
            "classes": ["r43"],
            "ratio": "43"
        },
        {
            "path": "images/france/paris",
            "fileName": "paris_04.jpg",
            "title": "",
            "year": "2016",
            "country": "France",
            "city": "Paris",
            "location": "Rue Germaine-Tailleferre (19e)",
            "classes": ["r43"],
            "ratio": "43"
        },
        {
            "path": "images/france/paris",
            "fileName": "paris_05.jpg",
            "title": "",
            "year": "2016",
            "country": "France",
            "city": "Paris",
            "location": "Rue Germaine-Tailleferre (19e)",
            "classes": ["r43"],
            "ratio": "43"
        },
        {
            "path": "images/france/paris",
            "fileName": "paris_06.jpg",
            "title": "",
            "year": "2016",
            "country": "France",
            "city": "Paris",
            "location": "Rue Germaine-Tailleferre (19e)",
            "classes": ["r32"],
            "ratio": "32"
        },
        {
            "path": "images/france/paris",
            "fileName": "paris_07.jpg",
            "title": "",
            "year": "2016",
            "country": "France",
            "city": "Paris",
            "location": "13e",
            "classes": ["r32"],
            "ratio": "32"
        },
        {
            "path": "images/france/paris",
            "fileName": "paris_08.jpg",
            "title": "",
            "year": "2016",
            "country": "France",
            "city": "Paris",
            "location": "",
            "classes": ["r32"],
            "ratio": "32"
        },
        {
            "path": "images/france/paris",
            "fileName": "paris_09.jpg",
            "title": "",
            "year": "2016",
            "country": "France",
            "city": "Paris",
            "location": "\"Le Mur\" Oberkampf",
            "classes": ["r32"],
            "ratio": "32"
        },
        {
            "path": "images/france/paris",
            "fileName": "paris_10.jpg",
            "title": "",
            "year": "2017",
            "country": "France",
            "city": "Paris",
            "location": "13e",
            "classes": ["r43"],
            "ratio": "43"
        },
        {
            "path": "images/france/paris",
            "fileName": "paris_11.jpg",
            "title": "",
            "year": "2018",
            "country": "France",
            "city": "Paris",
            "location": "Montmartre",
            "classes": ["r32"],
            "ratio": "32"
        },
        {
            "path": "images/france/paris",
            "fileName": "paris_12.jpg",
            "title": "",
            "year": "2016",
            "country": "France",
            "city": "Paris",
            "location": "",
            "classes": ["r43"],
            "ratio": "43"
        },
        {
            "path": "images/france/paris",
            "fileName": "paris_13.jpg",
            "title": "",
            "year": "2016",
            "country": "France",
            "city": "Paris",
            "location": "Galerie de l'Ourq (19e)",
            "classes": ["r43"],
            "ratio": "43"
        },
        {
            "path": "images/france/paris",
            "fileName": "paris_14.jpg",
            "title": "",
            "year": "2016",
            "country": "France",
            "city": "Paris",
            "location": "Rue Dénoyez (20e)",
            "classes": ["r43"],
            "ratio": "43"
        },
        {
            "path": "images/france/paris",
            "fileName": "paris_15.jpg",
            "title": "",
            "year": "2016",
            "country": "France",
            "city": "Paris",
            "location": "Rue Dénoyez (20e)",
            "classes": ["r43"],
            "ratio": "43"
        },
        {
            "path": "images/france/paris",
            "fileName": "paris_16.jpg",
            "title": "",
            "year": "2016",
            "country": "France",
            "city": "Paris",
            "location": "Place de la République",
            "classes": ["r32"],
            "ratio": "32"
        },
        {
            "path": "images/france/paris",
            "fileName": "paris_17.jpg",
            "title": "",
            "year": "2016",
            "country": "France",
            "city": "Paris",
            "location": "Place de la République",
            "classes": ["r32"],
            "ratio": "32"
        },
        {
            "path": "images/france/paris",
            "fileName": "paris_18.jpg",
            "title": "",
            "year": "2016",
            "country": "France",
            "city": "Paris",
            "location": "Place de la République",
            "classes": ["r32"],
            "ratio": "32"
        },
        {
            "path": "images/france/marseille",
            "fileName": "marseille_08.jpg",
            "title": "",
            "year": "2017",
            "country": "France",
            "city": "Marseille",
            "location": "",
            "classes": ["r32"],
            "ratio": "32"
        },
        {
            "path": "images/france/marseille",
            "fileName": "marseille_09.jpg",
            "title": "",
            "year": "2017",
            "country": "France",
            "city": "Marseille",
            "location": "Rue des 3 Rois",
            "classes": ["r32"],
            "ratio": "32"
        },
        {
            "path": "images/france/marseille",
            "fileName": "marseille_10.jpg",
            "title": "",
            "year": "2017",
            "country": "France",
            "city": "Marseille",
            "location": "",
            "classes": ["r32"],
            "ratio": "32"
        },
        {
            "path": "images/france/marseille",
            "fileName": "marseille_11.jpg",
            "title": "",
            "year": "2017",
            "country": "France",
            "city": "Marseille",
            "location": "",
            "classes": ["r32"],
            "ratio": "32"
        },
        {
            "path": "images/france/marseille",
            "fileName": "marseille_12.jpg",
            "title": "",
            "year": "2017",
            "country": "France",
            "city": "Marseille",
            "location": "",
            "classes": ["r32"],
            "ratio": "32"
        },
        {
            "path": "images/france/marseille",
            "fileName": "marseille_13.jpg",
            "title": "",
            "year": "2017",
            "country": "France",
            "city": "Marseille",
            "location": "",
            "classes": ["r32"],
            "ratio": "32"
        },
        {
            "path": "images/france/marseille",
            "fileName": "marseille_14.jpg",
            "title": "",
            "year": "2017",
            "country": "France",
            "city": "Marseille",
            "location": "",
            "classes": ["r32"],
            "ratio": "32"
        },
        {
            "path": "images/france/marseille",
            "fileName": "marseille_15.jpg",
            "title": "",
            "year": "2017",
            "country": "France",
            "city": "Marseille",
            "location": "",
            "classes": ["r43"],
            "ratio": "43"
        },
        {
            "path": "images/france/marseille",
            "fileName": "marseille_16.jpg",
            "title": "",
            "year": "2017",
            "country": "France",
            "city": "Marseille",
            "location": "",
            "classes": ["r32"],
            "ratio": "32"
        },
        {
            "path": "images/france/marseille",
            "fileName": "marseille_17.jpg",
            "title": "",
            "year": "2017",
            "country": "France",
            "city": "Marseille",
            "location": "",
            "classes": ["r43"],
            "ratio": "43"
        },
        {
            "path": "images/germany/berlin",
            "fileName": "berlin_04.jpg",
            "title": "",
            "year": "2018",
            "country": "Germany",
            "city": "Berlin",
            "location": "East Side Gallery",
            "classes": ["r32"],
            "ratio": "32"
        },
        {
            "path": "images/germany/berlin",
            "fileName": "berlin_05.jpg",
            "title": "",
            "year": "2018",
            "country": "Germany",
            "city": "Berlin",
            "location": "East Side Gallery",
            "classes": ["r43"],
            "ratio": "43"
        },
        {
            "path": "images/germany/berlin",
            "fileName": "berlin_06.jpg",
            "title": "",
            "year": "2018",
            "country": "Germany",
            "city": "Berlin",
            "location": "East Side Gallery",
            "classes": ["r43"],
            "ratio": "43"
        },
        {
            "path": "images/germany/berlin",
            "fileName": "berlin_07.jpg",
            "title": "",
            "year": "2018",
            "country": "Germany",
            "city": "Berlin",
            "location": "East Side Gallery",
            "classes": ["r32"],
            "ratio": "32"
        },
        {
            "path": "images/germany/berlin",
            "fileName": "berlin_08.jpg",
            "title": "",
            "year": "2018",
            "country": "Germany",
            "city": "Berlin",
            "location": "East Side Gallery",
            "classes": ["r43"],
            "ratio": "43"
        },
        {
            "path": "images/germany/berlin",
            "fileName": "berlin_09.jpg",
            "title": "",
            "year": "2018",
            "country": "Germany",
            "city": "Berlin",
            "location": "East Side Gallery",
            "classes": ["r32"],
            "ratio": "32"
        },
        {
            "path": "images/japan/tokyo",
            "fileName": "tokyo_02.jpg",
            "title": "",
            "year": "2016",
            "country": "Japan",
            "city": "Tokyo",
            "location": "Takeda no baba",
            "classes": ["r32"],
            "ratio": "32"
        },
        {
            "path": "images/japan/osaka",
            "fileName": "osaka_02.jpg",
            "title": "",
            "year": "2014",
            "country": "Japan",
            "city": "Osaka",
            "location": "Tsuruhashi",
            "classes": ["r43"],
            "ratio": "43"
        },
        {
            "path": "images/japan/kobe",
            "fileName": "kobe_harbour.jpg",
            "title": "",
            "year": "2014",
            "country": "Japan",
            "city": "Kobe",
            "location": "Meriken Park",
            "classes": ["r43"],
            "ratio": "43"
        },
        {
            "path": "images/czech_republic/prague",
            "fileName": "prague_04.jpg",
            "title": "",
            "year": "2018",
            "country": "Czech Republic",
            "city": "Prague",
            "location": "",
            "classes": ["r32"],
            "ratio": "32"
        },
        {
            "path": "images/czech_republic/prague",
            "fileName": "prague_05.jpg",
            "title": "",
            "year": "2018",
            "country": "Czech Republic",
            "city": "Prague",
            "location": "",
            "classes": ["r43"],
            "ratio": "43"
        },
        {
            "path": "images/czech_republic/prague",
            "fileName": "prague_06.jpg",
            "title": "",
            "year": "2018",
            "country": "Czech Republic",
            "city": "Prague",
            "location": "",
            "classes": ["r43"],
            "ratio": "43"
        },
        {
            "path": "images/czech_republic/prague",
            "fileName": "prague_07.jpg",
            "title": "",
            "year": "2018",
            "country": "Czech Republic",
            "city": "Prague",
            "location": "",
            "classes": ["r32"],
            "ratio": "32"
        },
        {
            "path": "images/czech_republic/prague",
            "fileName": "prague_08.jpg",
            "title": "",
            "year": "2018",
            "country": "Czech Republic",
            "city": "Prague",
            "location": "",
            "classes": ["r32"],
            "ratio": "32"
        },
        {
            "path": "images/czech_republic/prague",
            "fileName": "prague_09.jpg",
            "title": "",
            "year": "2018",
            "country": "Czech Republic",
            "city": "Prague",
            "location": "",
            "classes": ["r43"],
            "ratio": "43"
        },
        {
            "path": "images/czech_republic/prague",
            "fileName": "prague_10.jpg",
            "title": "",
            "year": "2018",
            "country": "Czech Republic",
            "city": "Prague",
            "location": "",
            "classes": ["r43"],
            "ratio": "43"
        },
        {
            "path": "images/czech_republic/prague",
            "fileName": "prague_11.jpg",
            "title": "",
            "year": "2018",
            "country": "Czech Republic",
            "city": "Prague",
            "location": "",
            "classes": ["r32"],
            "ratio": "32"
        },
        {
            "path": "images/uae/dubai",
            "fileName": "dubai_04.jpg",
            "title": "",
            "year": "2017",
            "country": "UAE",
            "city": "Dubai",
            "location": "",
            "classes": ["r32"],
            "ratio": "32"
        },
        {
            "path": "images/uae/dubai",
            "fileName": "dubai_05.jpg",
            "title": "",
            "year": "2017",
            "country": "UAE",
            "city": "Dubai",
            "location": "",
            "classes": ["r43"],
            "ratio": "43"
        },
        {
            "path": "images/uae/dubai",
            "fileName": "dubai_06.jpg",
            "title": "",
            "year": "2017",
            "country": "UAE",
            "city": "Dubai",
            "location": "Jumeirah",
            "classes": ["r43"],
            "ratio": "43"
        },
        {
            "path": "images/uae/dubai",
            "fileName": "dubai_07.jpg",
            "title": "",
            "year": "2017",
            "country": "UAE",
            "city": "Dubai",
            "location": "Jumeirah",
            "classes": ["r43"],
            "ratio": "43"
        },
        {
            "path": "images/uae/dubai",
            "fileName": "dubai_08.jpg",
            "title": "",
            "year": "2017",
            "country": "UAE",
            "city": "Dubai",
            "location": "Jumeirah",
            "classes": ["portrait"],
            "ratio": "z"
        }
    ]
}